osri/__init__.py
osri/cli.py
osri/config.py
osri/errors.py
osri-0.1.1.dist-info/entry_points.txt
osri-0.1.1.dist-info/LICENSE
osri-0.1.1.dist-info/WHEEL
osri-0.1.1.dist-info/METADATA
osri-0.1.1.dist-info/RECORD
