Metadata-Version: 2.1
Name: osri
Version: 0.1.1
Summary: Displays os info based on /etc/os-release
License: MIT
Author: odra
Author-email: me@lrossetti.com
Requires-Python: >=3.11,<4.0
Classifier: License :: OSI Approved :: MIT License
Classifier: Programming Language :: Python :: 3
Requires-Dist: click (>=8.1.3,<9.0.0)
Requires-Dist: prettytable (>=3.7.0,<4.0.0)
